MKE_M17/L9110_I2C.py
MKE_M17/__init__.py
driver_l9110_i2c-25.3.13.0.dist-info/LICENSE
driver_l9110_i2c-25.3.13.0.dist-info/METADATA
driver_l9110_i2c-25.3.13.0.dist-info/WHEEL
driver_l9110_i2c-25.3.13.0.dist-info/top_level.txt
driver_l9110_i2c-25.3.13.0.dist-info/RECORD
