Metadata-Version: 2.2
Name: Driver_L9110_i2c
Version: 25.3.13.0
Summary: A package for controlling JetRacer
Author-email: Quy-An <quyan18b@gmail.com>
Requires-Python: >=3.11
License-File: LICENSE
Requires-Dist: smbus>=1.1.post2
